<?xml version="1.0" encoding="UTF-8"?>
<rootTag>
<Award>
<AwardTitle><![CDATA[Support for the World Climate Research Programme]]></AwardTitle>
<AGENCY>NSF</AGENCY>
<AwardEffectiveDate>09/15/2021</AwardEffectiveDate>
<AwardExpirationDate>08/31/2024</AwardExpirationDate>
<AwardTotalIntnAmount>653325.00</AwardTotalIntnAmount>
<AwardAmount>653325</AwardAmount>
<AwardInstrument>
<Value>Standard Grant</Value>
</AwardInstrument>
<Organization>
<Code>06010000</Code>
<Directorate>
<Abbreviation>GEO</Abbreviation>
<LongName>Directorate For Geosciences</LongName>
</Directorate>
<Division>
<Abbreviation>RISE</Abbreviation>
<LongName>Div of Res, Innovation, Synergies, &amp; Edu</LongName>
</Division>
</Organization>
<ProgramOfficer>
<SignBlockName>Lina Patino</SignBlockName>
<PO_EMAI>lpatino@nsf.gov</PO_EMAI>
<PO_PHON>7032925047</PO_PHON>
</ProgramOfficer>
<AbstractNarration><![CDATA[This award supports the World Climate Research Programme (WCRP). WCRP is taking the lead in ensuring that the global, regional, and national climate research communities create the enduring, rigorous and scientific foundation required to meet the urgent demand for robust and useful regional climate information. WCRP is pursuing – through international coordination – frontier scientific questions related to the coupled climate system that are too large and too complex to be tackled by a single nation, agency, institution, or scientific discipline. In doing so, WCRP brings together scientists from the US and around the world, at all stages of their careers, to advance the understanding of the multi-scale dynamic interactions between components of the climate system and external forcing factors, as well as addressing and studying the role of humans on climate and society. WCRP informs the development of policies and operationally focused climate services, and promotes science capacity building and education in partnership with other programs.&lt;br/&gt;&lt;br/&gt;Hubs for modeling and observations capabilities and for regional climate information for society will facilitate international coordination of the activities. The expected outcomes would include integrated capabilities for warning and prediction on global and regional scales at the multi-annual to decadal timescales; climate information meaningful at the local scale; approaches that take into account human and natural systems; and digital and dynamic computational models that represent past, current, and possible future conditions on the Earth. WCRP also contributes significantly through its collaboration with national and international scientific partners to conducting sustained assessments,  communication and education. WCRP activities contribute directly to the goals of the US Global Change Research Program.&lt;br/&gt;&lt;br/&gt;This award reflects NSF's statutory mission and has been deemed worthy of support through evaluation using the Foundation's intellectual merit and broader impacts review criteria.]]></AbstractNarration>
<MinAmdLetterDate>09/16/2021</MinAmdLetterDate>
<MaxAmdLetterDate>09/16/2021</MaxAmdLetterDate>
<ARRAAmount/>
<TRAN_TYPE>Grant</TRAN_TYPE>
<CFDA_NUM>47.050</CFDA_NUM>
<NSF_PAR_USE_FLAG>1</NSF_PAR_USE_FLAG>
<FUND_AGCY_CODE>4900</FUND_AGCY_CODE>
<AWDG_AGCY_CODE>4900</AWDG_AGCY_CODE>
<AwardID>2040432</AwardID>
<Investigator>
<FirstName>Detlef</FirstName>
<LastName>Stammer</LastName>
<PI_MID_INIT>B</PI_MID_INIT>
<PI_SUFX_NAME/>
<PI_FULL_NAME>Detlef B Stammer</PI_FULL_NAME>
<EmailAddress><![CDATA[detlef.stammer@uni-hamburg.de]]></EmailAddress>
<NSF_ID>000473586</NSF_ID>
<StartDate>09/16/2021</StartDate>
<EndDate/>
<RoleCode>Principal Investigator</RoleCode>
</Investigator>
<Institution>
<Name>WORLD METEOROLOGICAL ORGANIZATION</Name>
<CityName>GENEVE</CityName>
<ZipCode>1202</ZipCode>
<PhoneNumber>0227308486</PhoneNumber>
<StreetAddress>AVENUE DE LA PAIX 7BIS</StreetAddress>
<StreetAddress2/>
<CountryName>Switzerland</CountryName>
<StateName/>
<StateCode>GE</StateCode>
<CONGRESSDISTRICT/>
<CONGRESS_DISTRICT_ORG/>
<ORG_UEI_NUM>RMMAX265BEM3</ORG_UEI_NUM>
<ORG_LGL_BUS_NAME>WORLD METEOROLOGICAL ORGANIZATION</ORG_LGL_BUS_NAME>
<ORG_PRNT_UEI_NUM>FGN3U2778FG2</ORG_PRNT_UEI_NUM>
</Institution>
<Performance_Institution>
<Name><![CDATA[WMO]]></Name>
<CityName>Geneva</CityName>
<StateCode/>
<ZipCode/>
<StreetAddress><![CDATA[AVENUE DE LA PAIX 7BIS]]></StreetAddress>
<CountryCode>SZ</CountryCode>
<CountryName>Switzerland</CountryName>
<StateName>RI REQUIRED</StateName>
<CountryFlag>0</CountryFlag>
<CONGRESSDISTRICT/>
<CONGRESS_DISTRICT_PERF/>
</Performance_Institution>
<ProgramElement>
<Code>1321</Code>
<Text>Decision, Risk &amp; Mgmt Sci</Text>
</ProgramElement>
<ProgramElement>
<Code>1577</Code>
<Text>GLOBAL CHANGE</Text>
</ProgramElement>
<ProgramElement>
<Code>7313</Code>
<Text>Intl Global Change Res &amp; Coord</Text>
</ProgramElement>
<ProgramElement>
<Code>V250</Code>
<Text/>
</ProgramElement>
<ProgramReference>
<Code>1679</Code>
<Text>INTERNATIONAL COORDINATION ACT</Text>
</ProgramReference>
<ProgramReference>
<Code>EGCH</Code>
<Text>ENVIRONMENT AND GLOBAL CHANGE</Text>
</ProgramReference>
<Appropriation>
<Code>0121</Code>
<Name>NSF RESEARCH &amp; RELATED ACTIVIT</Name>
<APP_SYMB_ID>040100</APP_SYMB_ID>
</Appropriation>
<Appropriation>
<Code>0121</Code>
<Name>NSF RESEARCH &amp; RELATED ACTIVIT</Name>
<APP_SYMB_ID>040100</APP_SYMB_ID>
</Appropriation>
<Appropriation>
<Code>02XX</Code>
<Name>NSF RESEARCH &amp; RELATED ACTIVIT</Name>
<APP_SYMB_ID>040100</APP_SYMB_ID>
</Appropriation>
<Fund>
<Code>01002122RB</Code>
<Name><![CDATA[NSF RESEARCH & RELATED ACTIVIT]]></Name>
<FUND_SYMB_ID>040100</FUND_SYMB_ID>
</Fund>
<Fund>
<Code>01002122DB</Code>
<Name><![CDATA[NSF RESEARCH & RELATED ACTIVIT]]></Name>
<FUND_SYMB_ID>040100</FUND_SYMB_ID>
</Fund>
<Fund>
<Code>0100XXXXDB</Code>
<Name><![CDATA[NSF RESEARCH & RELATED ACTIVIT]]></Name>
<FUND_SYMB_ID>040100</FUND_SYMB_ID>
</Fund>
<FUND_OBLG>2021~653325</FUND_OBLG>
</Award>
</rootTag>
